semantic_syntax_tree/__init__.py
semantic_syntax_tree/_git.py
semantic_syntax_tree/_logging.py
semantic_syntax_tree/api.py
semantic_syntax_tree/cli.py
semantic_syntax_tree/context.py
semantic_syntax_tree/database.py
semantic_syntax_tree/image_tests.py
semantic_syntax_tree/models.py
semantic_syntax_tree/parsers.py
semantic_syntax_tree/search.py
semantic_syntax_tree/sync.py
semantic_syntax_tree-0.2.0.dist-info/LICENSE
semantic_syntax_tree-0.2.0.dist-info/METADATA
semantic_syntax_tree-0.2.0.dist-info/WHEEL
semantic_syntax_tree-0.2.0.dist-info/entry_points.txt
semantic_syntax_tree-0.2.0.dist-info/top_level.txt
semantic_syntax_tree-0.2.0.dist-info/RECORD
